{
  "@context": "https://datascence.ca/context.jsonld",
  "type": "Spectacle",
  "identifier": [
    "http://lavitrine.com/spectacle/123456"
  ],
  "name": [
    {
      "lang": "fr",
      "value": "Hommage à Michel Louvain."
    }
  ],
  "description": [
    {
      "lang": "fr",
      "value": "Le 14 avril 2021, Michel Louvain tirait sa révérence après une vie dédiée à la chanson. Réunis sur scène dans cette production à l’image de..."
    }
  ],
  "média": [
    {
      "type": "Média",
      "url": "https://sallealbertrousseau.blob.core.windows.net/image-processor-cache/9/7/5/4/a/e/9754aef29c7eb9c559bb6bd4f55a0a8012e7c393.jpg",
      "notesUsage": "(ne sont pas affichées)"
    }
  ],
  "aContribution": [
    {
      "type": "Contribution",
      "contributionType": [
        {
          "type": "Term",
          "vocabulary": "ContributionType",
          "code": "ArtisteSurScène",
          "label": [
            {
              "lang": "fr",
              "value": "Production"
            }
          ],
          "sequenceNumber": 1
        }
      ],
      "contributeur": {
        "type": "Contributeur",
        "typeContributeur": "PersonnePhysique",
        "identifier": [
          "http://lavitrine.com/123456"
        ],
        "name": [
          {
            "lang": "fr",
            "value": "Un certain souvenir"
          }
        ],
        "aAssociationGéographique": [
          {
            "type": "AssociationGéographique",
            "typeAssociationGéographique": {
              "type": "Term",
              "vocabulary": "AssociationGéographiqueType",
              "code": "lieuDeFondation",
              "label": [
                {
                  "lang": "fr",
                  "value": "Lieu de fondation"
                }
              ],
              "sequenceNumber": 1
            },
            "pays": "CAN",
            "région": "QC",
            "ville": "Québec"
          }
        ]
      }
    }
  ],
  "mainEntityOfPage": [
    {
      "type": "WebPage",
      "url": "https://www.sallealbertrousseau.com/programmation/un-certain-souvenir/",
      "inLanguage": "fr"
    },
    {
      "type": "WebPage",
      "url": "https://www.sallealbertrousseau.com/events/un-certain-souvenir/",
      "inLanguage": "en"
    }
  ],
  "discipline": [
    {
      "type": "Term",
      "vocabulary": "Discipline",
      "code": "Chanson",
      "label": [
        {
          "lang": "fr",
          "value": "Chanson"
        }
      ],
      "sequenceNumber": 1
    }
  ],
  "publicCible": [
    {
      "type": "Term",
      "vocabulary": "PublicCible",
      "code": "ToutPublics",
      "label": [
        {
          "lang": "fr",
          "value": "Tout publics"
        }
      ],
      "sequenceNumber": 1
    }
  ],
  "enLangue": [
    "fr"
  ],
  "spectacleSansParole": false,
  "aReprésentation": [
    {
      "type": "Représentation",
      "identifier": [
        "http://lavitrine.com/representation/123456"
      ],
      "début": "2023-02-26T15:00:00-05:00",
      "inSeries": [
        {
          "type": "Série",
          "début": "2023-02-26T15:00:00-05:00",
          "description": [
            {
              "lang": "fr",
              "value": "Un certain souvenir est une série de spectacles qui rendent hommage à Michel Louvain."
            }
          ],
          "identifier": [
            "http://lavitrine.com/series/123456"
          ],
          "name": [
            {
              "lang": "fr",
              "value": "Un certain souvenir"
            }
          ]
        }
      ],
      "aOffre": [
        {
          "type": "Offre",
          "hasRoomConfiguration": {
            "type": "RoomConfiguration",
            "layout": {
              "type": "Term",
              "vocabulary": "ConfigurationSalleType",
              "code": "Cabaret",
              "label": [
                {
                  "lang": "fr",
                  "value": "Configuration salle type 1"
                }
              ],
              "sequenceNumber": 1
            }
          },
          "aLieu": {
            "type": "Place",
            "virtualPlace": false,
            "identifier": [
              "http://lavitrine.com/representation/7567567"
            ],
            "name": [
              {
                "lang": "fr",
                "value": "Salle Albert-Rousseau"
              }
            ],
            "address": {
              "type": "PostalAddress",
              "streetAddress": "250 Sainte-Foy",
              "addressLocality": "Québec",
              "addressRegion": "QC",
              "addressCountry": "CAN",
              "postalCode": "G1V 1T3"
            }
          },
          "complet": false,
          "statut": "EventScheduled",
          "gratuit": false,
          "accessibleViaAutreOffre": false,
          "sansLienAcquisition": false,
          "lienAcquisition": "https://www.sallealbertrousseau.com/programmation/un-certain-souvenir/"
        }
      ]
    }
  ]
}